{
    "pycharm64.exe": {
        "app_name": "PyCharm Community Edition",
        "icon_path": "project_icons\\pycharm64.png"
    },
    "explorer.exe": {
        "app_name": "Windows Explorer",
        "icon_path": "project_icons\\explorer.png"
    },
    "vivaldi.exe": {
        "app_name": "Vivaldi",
        "icon_path": "project_icons\\vivaldi.png"
    },
    "spotify.exe": {
        "app_name": "Spotify",
        "icon_path": "project_icons\\Spotify.png"
    },
    "sourcetree.exe": {
        "app_name": "Sourcetree",
        "icon_path": "project_icons\\SourceTree.png"
    },
    "photos.exe": {
        "app_name": "Unknown App",
        "icon_path": ""
    },
    "csrss.exe": {
        "app_name": "Client Server Runtime Process",
        "icon_path": ""
    },
    "notepad.exe": {
        "app_name": "Notepad",
        "icon_path": "project_icons\\notepad.png"
    },
    "photoshop.exe": {
        "app_name": "Adobe Photoshop 2024",
        "icon_path": "project_icons\\Photoshop.png"
    },
    "flux.exe": {
        "app_name": "f.lux",
        "icon_path": "project_icons\\flux.png"
    },
    "blender.exe": {
        "app_name": "Blender",
        "icon_path": "project_icons\\blender.png"
    },
    "powertoys.advancedpaste.exe": {
        "app_name": "PowerToys.AdvancedPaste",
        "icon_path": "project_icons\\PowerToys.AdvancedPaste.png"
    }
}